beamfed/__init__.py
beamfed/__main__.py
beamfed/files.py
beamfed/datafed_wrapper/__init__.py
beamfed/datafed_wrapper/__main__.py
beamfed/datafed_wrapper/collection.py
beamfed/datafed_wrapper/data_record.py
beamfed/datafed_wrapper/protobuf.py
beamfed/datafed_wrapper/task_list.py
beamfed/datafed_wrapper/verify.py
beamfed-0.0.1.dist-info/LICENSE
beamfed-0.0.1.dist-info/METADATA
beamfed-0.0.1.dist-info/WHEEL
beamfed-0.0.1.dist-info/top_level.txt
beamfed-0.0.1.dist-info/RECORD
