Metadata-Version: 2.1
Name: beamfed
Version: 0.0.1
Summary: A DataFed wrapper for beamline data
Home-page: https://github.com/JBlaschke/BeamFed
Author: Johannes Blaschke
Author-email: johannes@blaschke.science
License: UNKNOWN
Platform: UNKNOWN
Classifier: Programming Language :: Python :: 3
Classifier: License :: OSI Approved :: MIT License
Classifier: Operating System :: OS Independent
Requires-Python: >=3.6
Requires-Dist: datafed
